{
  "locale": "en-US",
  "translations": {
    "3174354408404578867": "About {$INTERPOLATION}",
    "6439365426343089851": "General",
    "7136888919962092730": "Changelog",
    "4637334248246674819": "Libraries",
    "3113844851981371723": "System info",
    "1289394110135916208": "Show log",
    "1853401546881470119": " {$INTERPOLATION} was primarily developed by {$START_LINK}{$INTERPOLATION_1}{$CLOSE_LINK} and {$START_LINK_1}{$INTERPOLATION_2}{$CLOSE_LINK}. {$INTERPOLATION} can be downloaded from {$START_LINK_2}{$INTERPOLATION_3}{$CLOSE_LINK}. {$INTERPOLATION} is licensed under the {$START_LINK_3}{$INTERPOLATION_4}{$CLOSE_LINK}. ",
    "4415472305681448513": "You are currently running {$INTERPOLATION} {$INTERPOLATION_1}",
    "2461382652393691576": "Check for updates now",
    "1466693861558509914": "Checking for updates …",
    "1555072599383288019": "Loading …",
    "483279741770305070": "System properties",
    "5851834152954326369": "Backend modules: ",
    "4401413517116848484": "Compression modules: ",
    "1829912491024466963": "Encryption modules: ",
    "6373244879270616351": "Server state properties",
    "6196598158183149717": "Activate failed: ",
    "4491027740832706620": "Add a new backup",
    "1376726197773934065": "Configure a new backup",
    "732184635043894669": "Enter configuration details",
    "2290751141464634328": "Import from a file",
    "4275782396438377102": "Load a configuration from an exported job or a storage provider",
    "4901550848413234188": "Next >",
    "4412958068611913614": "custom",
    "8875746834087652962": "Remove option",
    "3890802194371764820": "Add advanced option",
    "3944619200216995090": "- pick an option -",
    "3576013801787566643": "Use existing database?",
    "5953072959542552454": "An existing local database for the storage has been found.\nRe-using the database will allow the command-line and server instances to work on the same remote storage.\n\n Do you wish to use the existing database?",
    "2159130950882492111": "Cancel",
    "2807800733729323332": "Yes",
    "3542042671420335679": "No",
    "77522255637065336": "Connection error",
    "1768080250171346153": "Missing passphrase",
    "4772108103810676934": "You must enter a passphrase or disable encryption",
    "913080034641856612": "Non-matching passphrase",
    "5640601541577053867": "Passphrases are not matching",
    "4005385996502339280": "Autogenerated passphrase",
    "6283062901699355302": "You have generated a strong passphrase. Make sure you have made a safe copy of the passphrase, as the data cannot be recovered if you lose the passphrase.",
    "8493894841653115510": "Yes, I have stored the passphrase safely",
    "1878963332781171374": "Passphrase changed",
    "1187625789875993518": "You have changed the passphrase, which is not supported. You are encouraged to create a new backup instead.",
    "6173421524731167371": "Yes, please break my backup!",
    "4212465305158913746": "Encryption changed",
    "595774955369350263": "You have changed the encryption mode. This may break stuff. You are encouraged to create a new backup instead",
    "137821994032651287": "Yes, I'm brave!",
    "451418349275958054": "No encryption",
    "1956250369271903839": "You have chosen not to encrypt the backup. Encryption is recommended for all data stored on a remote server.",
    "6994632191151160314": "Continue without encryption",
    "6924129870335819185": "Weak passphrase",
    "2885436428274998757": "Your passphrase is easy to guess. Consider changing passphrase.",
    "8507694615256745050": "Use weak passphrase",
    "1519954996184640001": "Error"
  }
}